ue4cli/CMakeCustomFlags.py
ue4cli/CachedDataManager.py
ue4cli/ConfigurationManager.py
ue4cli/JsonDataManager.py
ue4cli/PluginManager.py
ue4cli/ThirdPartyLibraryDetails.py
ue4cli/UE4BuildInterrogator.py
ue4cli/UnrealManagerBase.py
ue4cli/UnrealManagerDarwin.py
ue4cli/UnrealManagerException.py
ue4cli/UnrealManagerFactory.py
ue4cli/UnrealManagerLinux.py
ue4cli/UnrealManagerUnix.py
ue4cli/UnrealManagerWindows.py
ue4cli/Utility.py
ue4cli/__init__.py
ue4cli/__main__.py
ue4cli/cli.py
ue4cli-0.0.54.dist-info/LICENSE
ue4cli-0.0.54.dist-info/METADATA
ue4cli-0.0.54.dist-info/WHEEL
ue4cli-0.0.54.dist-info/entry_points.txt
ue4cli-0.0.54.dist-info/top_level.txt
ue4cli-0.0.54.dist-info/zip-safe
ue4cli-0.0.54.dist-info/RECORD
