Metadata-Version: 2.1
Name: ue4cli
Version: 0.0.54
Summary: Command-line interface for Unreal Engine 4
Home-page: http://github.com/adamrehn/ue4cli
Author: Adam Rehn
Author-email: adam@adamrehn.com
License: MIT
Keywords: epic unreal engine
Platform: UNKNOWN
Classifier: License :: OSI Approved :: MIT License
Classifier: Programming Language :: Python :: 3.5
Classifier: Programming Language :: Python :: 3.6
Classifier: Programming Language :: Python :: 3.7
Classifier: Topic :: Software Development :: Build Tools
Classifier: Environment :: Console
Requires-Python: >=3.5
Requires-Dist: setuptools (>=38.6.0)
Requires-Dist: shellescape
Requires-Dist: twine (>=1.11.0)
Requires-Dist: wheel (>=0.31.0)
